main.py
setup.py
pysisphus.egg-info/PKG-INFO
pysisphus.egg-info/SOURCES.txt
pysisphus.egg-info/dependency_links.txt
pysisphus.egg-info/requires.txt
pysisphus.egg-info/top_level.txt